test_release_workflow/__init__.py
test_release_workflow/_version.py
test_release_workflow-0.1.3.dist-info/LICENSE
test_release_workflow-0.1.3.dist-info/METADATA
test_release_workflow-0.1.3.dist-info/WHEEL
test_release_workflow-0.1.3.dist-info/top_level.txt
test_release_workflow-0.1.3.dist-info/RECORD
