Metadata-Version: 2.1
Name: test_release_workflow
Version: 0.1.3
Summary: A fake package that is only used to test pypi release automation
Author-email: Luciano Paz <luciano.paz@pymc-labs.io>
License: This is free and unencumbered software released into the public domain.
Project-URL: repository, https://github.com/lucianopaz/test_release_workflow
Classifier: Development Status :: 4 - Beta
Classifier: Programming Language :: Python
Classifier: Programming Language :: Python :: 3
Classifier: Programming Language :: Python :: 3.8
Classifier: Programming Language :: Python :: 3.9
Classifier: Programming Language :: Python :: 3.10
Classifier: Programming Language :: Python :: 3.11
Classifier: License :: OSI Approved :: The Unlicense (Unlicense)
Classifier: Intended Audience :: Developers
Classifier: Topic :: Education :: Testing
Classifier: Operating System :: OS Independent
Requires-Python: >=3.8
License-File: LICENSE
